<?xml version="1.0"?>
<MethodSetup Method="BDT::BDT">
  <GeneralInfo>
    <Info name="TMVA Release" value="4.2.1 [262657]"/>
    <Info name="ROOT Release" value="6.28/04 [400388]"/>
    <Info name="Creator" value="quibus"/>
    <Info name="Date" value="Wed Dec  6 16:31:23 2023"/>
    <Info name="Host" value="Linux 596e3a4dc29f 6.2.0-1015-azure #15~22.04.1-Ubuntu SMP Fri Oct 6 13:20:44 UTC 2023 x86_64 x86_64 x86_64 GNU/Linux"/>
    <Info name="Dir" value="/home/quibus/mva_analysis"/>
    <Info name="Training events" value="399133"/>
    <Info name="TrainingTime" value="1.38800271e+01"/>
    <Info name="AnalysisType" value="Classification"/>
  </GeneralInfo>
  <Options>
    <Option name="V" modified="Yes">False</Option>
    <Option name="VerbosityLevel" modified="No">Default</Option>
    <Option name="VarTransform" modified="No">None</Option>
    <Option name="H" modified="Yes">False</Option>
    <Option name="CreateMVAPdfs" modified="No">False</Option>
    <Option name="IgnoreNegWeightsInTraining" modified="No">False</Option>
    <Option name="NTrees" modified="Yes">10</Option>
    <Option name="MaxDepth" modified="Yes">3</Option>
    <Option name="MinNodeSize" modified="Yes">0.025</Option>
    <Option name="nCuts" modified="No">20</Option>
    <Option name="BoostType" modified="No">AdaBoost</Option>
    <Option name="AdaBoostR2Loss" modified="No">quadratic</Option>
    <Option name="UseBaggedBoost" modified="No">False</Option>
    <Option name="Shrinkage" modified="No">1.000000e+00</Option>
    <Option name="AdaBoostBeta" modified="No">5.000000e-01</Option>
    <Option name="UseRandomisedTrees" modified="No">False</Option>
    <Option name="UseNvars" modified="No">4</Option>
    <Option name="UsePoissonNvars" modified="No">True</Option>
    <Option name="BaggedSampleFraction" modified="No">6.000000e-01</Option>
    <Option name="UseYesNoLeaf" modified="No">True</Option>
    <Option name="NegWeightTreatment" modified="No">inverseboostnegweights</Option>
    <Option name="Css" modified="No">1.000000e+00</Option>
    <Option name="Cts_sb" modified="No">1.000000e+00</Option>
    <Option name="Ctb_ss" modified="No">1.000000e+00</Option>
    <Option name="Cbb" modified="No">1.000000e+00</Option>
    <Option name="NodePurityLimit" modified="No">5.000000e-01</Option>
    <Option name="SeparationType" modified="No">giniindex</Option>
    <Option name="RegressionLossFunctionBDTG" modified="No">huber</Option>
    <Option name="HuberQuantile" modified="No">7.000000e-01</Option>
    <Option name="DoBoostMonitor" modified="No">False</Option>
    <Option name="UseFisherCuts" modified="No">False</Option>
    <Option name="MinLinCorrForFisher" modified="No">8.000000e-01</Option>
    <Option name="UseExclusiveVars" modified="No">False</Option>
    <Option name="DoPreselection" modified="No">False</Option>
    <Option name="SigToBkgFraction" modified="No">1.000000e+00</Option>
    <Option name="PruneMethod" modified="No">nopruning</Option>
    <Option name="PruneStrength" modified="No">0.000000e+00</Option>
    <Option name="PruningValFraction" modified="No">5.000000e-01</Option>
    <Option name="SkipNormalization" modified="No">False</Option>
    <Option name="nEventsMin" modified="No">0</Option>
    <Option name="UseBaggedGrad" modified="No">False</Option>
    <Option name="GradBaggingFraction" modified="No">6.000000e-01</Option>
    <Option name="UseNTrainEvents" modified="No">0</Option>
    <Option name="NNodesMax" modified="No">0</Option>
  </Options>
  <Variables NVar="17">
    <Variable VarIndex="0" Expression="C_Ds_pt" Label="C_Ds_pt" Title="C_Ds_pt" Unit="" Internal="C_Ds_pt" Type="F" Min="1.00242968e+01" Max="1.04482288e+03"/>
    <Variable VarIndex="1" Expression="C_Ds_vertex_2DSig_BS" Label="C_Ds_vertex_2DSig_BS" Title="C_Ds_vertex_2DSig_BS" Unit="" Internal="C_Ds_vertex_2DSig_BS" Type="F" Min="4.02594218e-03" Max="7.03078857e+02"/>
    <Variable VarIndex="2" Expression="C_Ds_vertex_cos2D" Label="C_Ds_vertex_cos2D" Title="C_Ds_vertex_cos2D" Unit="" Internal="C_Ds_vertex_cos2D" Type="F" Min="-1.00000000e+00" Max="1.00000000e+00"/>
    <Variable VarIndex="3" Expression="C_Ds_vertex_prob" Label="C_Ds_vertex_prob" Title="C_Ds_vertex_prob" Unit="" Internal="C_Ds_vertex_prob" Type="F" Min="1.00005269e-02" Max="1.00000000e+00"/>
    <Variable VarIndex="4" Expression="C_Hnl_vertex_2DSig_BS" Label="C_Hnl_vertex_2DSig_BS" Title="C_Hnl_vertex_2DSig_BS" Unit="" Internal="C_Hnl_vertex_2DSig_BS" Type="F" Min="8.74681573e-05" Max="1.76542832e+04"/>
    <Variable VarIndex="5" Expression="C_Hnl_vertex_cos2D" Label="C_Hnl_vertex_cos2D" Title="C_Hnl_vertex_cos2D" Unit="" Internal="C_Hnl_vertex_cos2D" Type="F" Min="-1.00000000e+00" Max="1.00000000e+00"/>
    <Variable VarIndex="6" Expression="C_Hnl_vertex_cos3D" Label="C_Hnl_vertex_cos3D" Title="C_Hnl_vertex_cos3D" Unit="" Internal="C_Hnl_vertex_cos3D" Type="F" Min="-9.99999940e-01" Max="9.99999881e-01"/>
    <Variable VarIndex="7" Expression="C_Hnl_vertex_prob" Label="C_Hnl_vertex_prob" Title="C_Hnl_vertex_prob" Unit="" Internal="C_Hnl_vertex_prob" Type="F" Min="1.00010214e-02" Max="9.99998689e-01"/>
    <Variable VarIndex="8" Expression="C_mu_Ds_BS_ips_xy" Label="C_mu_Ds_BS_ips_xy" Title="C_mu_Ds_BS_ips_xy" Unit="" Internal="C_mu_Ds_BS_ips_xy" Type="F" Min="1.20786999e-05" Max="4.31166138e+02"/>
    <Variable VarIndex="9" Expression="C_mu_Ds_pt" Label="C_mu_Ds_pt" Title="C_mu_Ds_pt" Unit="" Internal="C_mu_Ds_pt" Type="F" Min="2.00012350e+00" Max="2.18071091e+02"/>
    <Variable VarIndex="10" Expression="C_mu_Hnl_BS_ips_xy" Label="C_mu_Hnl_BS_ips_xy" Title="C_mu_Hnl_BS_ips_xy" Unit="" Internal="C_mu_Hnl_BS_ips_xy" Type="F" Min="3.53938485e-05" Max="2.79604095e+02"/>
    <Variable VarIndex="11" Expression="C_mu_Hnl_pt" Label="C_mu_Hnl_pt" Title="C_mu_Hnl_pt" Unit="" Internal="C_mu_Hnl_pt" Type="F" Min="2.00002956e+00" Max="2.21482269e+02"/>
    <Variable VarIndex="12" Expression="C_pi_BS_ip_xy" Label="C_pi_BS_ip_xy" Title="C_pi_BS_ip_xy" Unit="" Internal="C_pi_BS_ip_xy" Type="F" Min="3.13294137e-08" Max="1.06804398e+02"/>
    <Variable VarIndex="13" Expression="C_pi_BS_ips_xy" Label="C_pi_BS_ips_xy" Title="C_pi_BS_ips_xy" Unit="" Internal="C_pi_BS_ips_xy" Type="F" Min="6.35279730e-06" Max="4.93649872e+02"/>
    <Variable VarIndex="14" Expression="C_pi_pt" Label="C_pi_pt" Title="C_pi_pt" Unit="" Internal="C_pi_pt" Type="F" Min="5.00488281e-01" Max="2.36125000e+02"/>
    <Variable VarIndex="15" Expression="C_mu1mu2_dr" Label="C_mu1mu2_dr" Title="C_mu1mu2_dr" Unit="" Internal="C_mu1mu2_dr" Type="F" Min="9.79517572e-05" Max="5.61493814e-01"/>
    <Variable VarIndex="16" Expression="C_mu2pi_dr" Label="C_mu2pi_dr" Title="C_mu2pi_dr" Unit="" Internal="C_mu2pi_dr" Type="F" Min="1.75024015e-05" Max="1.09859824e+00"/>
  </Variables>
  <Spectators NSpec="0"/>
  <Classes NClass="2">
    <Class Name="Signal" Index="0"/>
    <Class Name="Background" Index="1"/>
  </Classes>
  <Transformations NTransformations="0"/>
  <MVAPdfs/>
  <Weights NTrees="10" AnalysisType="0">
    <BinaryTree type="DecisionTree" boostWeight="7.8799591666023150e-01" itree="0">
      <Node pos="s" depth="0" NCoef="0" IVar="13" Cut="2.3507143020629883e+01" cType="0" res="-9.9000000000000000e+01" rms="0.0000000000000000e+00" purity="5.0000000000000000e-01" nType="0">
        <Node pos="l" depth="1" NCoef="0" IVar="-1" Cut="2.5292675018310547e+01" cType="1" res="-9.9000000000000000e+01" rms="0.0000000000000000e+00" purity="9.4202464818954468e-01" nType="1"/>
        <Node pos="r" depth="1" NCoef="0" IVar="13" Cut="5.5968523025512695e+00" cType="0" res="-9.9000000000000000e+01" rms="0.0000000000000000e+00" purity="2.8917655348777771e-01" nType="0">
          <Node pos="l" depth="2" NCoef="0" IVar="-1" Cut="1.7913104248046875e+02" cType="0" res="-9.9000000000000000e+01" rms="0.0000000000000000e+00" purity="5.8897781372070312e-01" nType="1"/>
          <Node pos="r" depth="2" NCoef="0" IVar="4" Cut="1.1825023651123047e+02" cType="0" res="-9.9000000000000000e+01" rms="0.0000000000000000e+00" purity="1.7222334444522858e-01" nType="0">
            <Node pos="l" depth="3" NCoef="0" IVar="-1" Cut="0.0000000000000000e+00" cType="1" res="-9.9000000000000000e+01" rms="0.0000000000000000e+00" purity="9.5063757896423340e-01" nType="1"/>
            <Node pos="r" depth="3" NCoef="0" IVar="-1" Cut="0.0000000000000000e+00" cType="1" res="-9.9000000000000000e+01" rms="0.0000000000000000e+00" purity="1.5530396997928619e-01" nType="-1"/>
          </Node>
        </Node>
      </Node>
    </BinaryTree>
    <BinaryTree type="DecisionTree" boostWeight="7.0990583892465486e-01" itree="1">
      <Node pos="s" depth="0" NCoef="0" IVar="13" Cut="2.3507143020629883e+01" cType="0" res="-9.9000000000000000e+01" rms="0.0000000000000000e+00" purity="4.8841470479965210e-01" nType="0">
        <Node pos="l" depth="1" NCoef="0" IVar="1" Cut="2.5292675018310547e+01" cType="1" res="-9.9000000000000000e+01" rms="0.0000000000000000e+00" purity="8.8079893589019775e-01" nType="0">
          <Node pos="l" depth="2" NCoef="0" IVar="-1" Cut="9.0929565429687500e+00" cType="0" res="-9.9000000000000000e+01" rms="0.0000000000000000e+00" purity="9.5675271749496460e-01" nType="1"/>
          <Node pos="r" depth="2" NCoef="0" IVar="4" Cut="1.6087944030761719e+02" cType="0" res="-9.9000000000000000e+01" rms="0.0000000000000000e+00" purity="5.2312773466110229e-01" nType="0">
            <Node pos="l" depth="3" NCoef="0" IVar="-1" Cut="0.0000000000000000e+00" cType="1" res="-9.9000000000000000e+01" rms="0.0000000000000000e+00" purity="9.5615953207015991e-01" nType="1"/>
            <Node pos="r" depth="3" NCoef="0" IVar="-1" Cut="0.0000000000000000e+00" cType="1" res="-9.9000000000000000e+01" rms="0.0000000000000000e+00" purity="3.5183554887771606e-01" nType="-1"/>
          </Node>
        </Node>
        <Node pos="r" depth="1" NCoef="0" IVar="4" Cut="1.7907974243164062e+02" cType="0" res="-9.9000000000000000e+01" rms="0.0000000000000000e+00" purity="3.3084902167320251e-01" nType="0">
          <Node pos="l" depth="2" NCoef="0" IVar="-1" Cut="1.1308023929595947e+00" cType="0" res="-9.9000000000000000e+01" rms="0.0000000000000000e+00" purity="9.8190319538116455e-01" nType="1"/>
          <Node pos="r" depth="2" NCoef="0" IVar="4" Cut="4.2525222778320312e+01" cType="0" res="-9.9000000000000000e+01" rms="0.0000000000000000e+00" purity="3.0396491289138794e-01" nType="0">
            <Node pos="l" depth="3" NCoef="0" IVar="-1" Cut="0.0000000000000000e+00" cType="1" res="-9.9000000000000000e+01" rms="0.0000000000000000e+00" purity="7.8061044216156006e-01" nType="1"/>
            <Node pos="r" depth="3" NCoef="0" IVar="-1" Cut="0.0000000000000000e+00" cType="1" res="-9.9000000000000000e+01" rms="0.0000000000000000e+00" purity="2.5231984257698059e-01" nType="-1"/>
          </Node>
        </Node>
      </Node>
    </BinaryTree>
    <BinaryTree type="DecisionTree" boostWeight="4.2049234657837403e-01" itree="2">
      <Node pos="s" depth="0" NCoef="0" IVar="13" Cut="2.3507143020629883e+01" cType="0" res="-9.9000000000000000e+01" rms="0.0000000000000000e+00" purity="5.5171048641204834e-01" nType="0">
        <Node pos="l" depth="1" NCoef="0" IVar="1" Cut="5.0563335418701172e+01" cType="1" res="-9.9000000000000000e+01" rms="0.0000000000000000e+00" purity="8.5404509305953979e-01" nType="0">
          <Node pos="l" depth="2" NCoef="0" IVar="-1" Cut="1.2982785224914551e+01" cType="0" res="-9.9000000000000000e+01" rms="0.0000000000000000e+00" purity="8.8890123367309570e-01" nType="1"/>
          <Node pos="r" depth="2" NCoef="0" IVar="13" Cut="4.2242687225341797e+01" cType="0" res="-9.9000000000000000e+01" rms="0.0000000000000000e+00" purity="4.1261684894561768e-01" nType="0">
            <Node pos="l" depth="3" NCoef="0" IVar="-1" Cut="0.0000000000000000e+00" cType="1" res="-9.9000000000000000e+01" rms="0.0000000000000000e+00" purity="5.5208122730255127e-01" nType="1"/>
            <Node pos="r" depth="3" NCoef="0" IVar="-1" Cut="0.0000000000000000e+00" cType="1" res="-9.9000000000000000e+01" rms="0.0000000000000000e+00" purity="2.1186862885951996e-01" nType="-1"/>
          </Node>
        </Node>
        <Node pos="r" depth="1" NCoef="0" IVar="6" Cut="9.0476179122924805e-01" cType="0" res="-9.9000000000000000e+01" rms="0.0000000000000000e+00" purity="4.4618737697601318e-01" nType="0">
          <Node pos="l" depth="2" NCoef="0" IVar="1" Cut="3.0766838073730469e+01" cType="1" res="-9.9000000000000000e+01" rms="0.0000000000000000e+00" purity="6.6957229375839233e-01" nType="0">
            <Node pos="l" depth="3" NCoef="0" IVar="-1" Cut="0.0000000000000000e+00" cType="1" res="-9.9000000000000000e+01" rms="0.0000000000000000e+00" purity="7.3646515607833862e-01" nType="1"/>
            <Node pos="r" depth="3" NCoef="0" IVar="-1" Cut="0.0000000000000000e+00" cType="1" res="-9.9000000000000000e+01" rms="0.0000000000000000e+00" purity="2.6843237876892090e-01" nType="-1"/>
          </Node>
          <Node pos="r" depth="2" NCoef="0" IVar="4" Cut="9.3123809814453125e+01" cType="0" res="-9.9000000000000000e+01" rms="0.0000000000000000e+00" purity="4.0007379651069641e-01" nType="0">
            <Node pos="l" depth="3" NCoef="0" IVar="-1" Cut="0.0000000000000000e+00" cType="1" res="-9.9000000000000000e+01" rms="0.0000000000000000e+00" purity="8.6802071332931519e-01" nType="1"/>
            <Node pos="r" depth="3" NCoef="0" IVar="-1" Cut="0.0000000000000000e+00" cType="1" res="-9.9000000000000000e+01" rms="0.0000000000000000e+00" purity="3.8808536529541016e-01" nType="-1"/>
          </Node>
        </Node>
      </Node>
    </BinaryTree>
    <BinaryTree type="DecisionTree" boostWeight="2.4228677287478312e-01" itree="3">
      <Node pos="s" depth="0" NCoef="0" IVar="13" Cut="4.7014278411865234e+01" cType="0" res="-9.9000000000000000e+01" rms="0.0000000000000000e+00" purity="5.8456879854202271e-01" nType="0">
        <Node pos="l" depth="1" NCoef="0" IVar="1" Cut="5.0579959869384766e+01" cType="1" res="-9.9000000000000000e+01" rms="0.0000000000000000e+00" purity="9.1935938596725464e-01" nType="0">
          <Node pos="l" depth="2" NCoef="0" IVar="-1" Cut="1.3018557548522949e+01" cType="0" res="-9.9000000000000000e+01" rms="0.0000000000000000e+00" purity="9.5620644092559814e-01" nType="1"/>
          <Node pos="r" depth="2" NCoef="0" IVar="1" Cut="9.6306518554687500e+01" cType="1" res="-9.9000000000000000e+01" rms="0.0000000000000000e+00" purity="4.7360461950302124e-01" nType="0">
            <Node pos="l" depth="3" NCoef="0" IVar="-1" Cut="0.0000000000000000e+00" cType="1" res="-9.9000000000000000e+01" rms="0.0000000000000000e+00" purity="5.6883442401885986e-01" nType="1"/>
            <Node pos="r" depth="3" NCoef="0" IVar="-1" Cut="0.0000000000000000e+00" cType="1" res="-9.9000000000000000e+01" rms="0.0000000000000000e+00" purity="2.7210596203804016e-01" nType="-1"/>
          </Node>
        </Node>
        <Node pos="r" depth="1" NCoef="0" IVar="15" Cut="8.0297358334064484e-02" cType="0" res="-9.9000000000000000e+01" rms="0.0000000000000000e+00" purity="5.3342813253402710e-01" nType="0">
          <Node pos="l" depth="2" NCoef="0" IVar="-1" Cut="2.9101646423339844e+01" cType="0" res="-9.9000000000000000e+01" rms="0.0000000000000000e+00" purity="5.5770099163055420e-01" nType="1"/>
          <Node pos="r" depth="2" NCoef="0" IVar="4" Cut="1.7907994079589844e+02" cType="0" res="-9.9000000000000000e+01" rms="0.0000000000000000e+00" purity="3.5955405235290527e-01" nType="0">
            <Node pos="l" depth="3" NCoef="0" IVar="-1" Cut="0.0000000000000000e+00" cType="1" res="-9.9000000000000000e+01" rms="0.0000000000000000e+00" purity="8.9429271221160889e-01" nType="1"/>
            <Node pos="r" depth="3" NCoef="0" IVar="-1" Cut="0.0000000000000000e+00" cType="1" res="-9.9000000000000000e+01" rms="0.0000000000000000e+00" purity="3.4018653631210327e-01" nType="-1"/>
          </Node>
        </Node>
      </Node>
    </BinaryTree>
    <BinaryTree type="DecisionTree" boostWeight="2.8984594690785642e-01" itree="4">
      <Node pos="s" depth="0" NCoef="0" IVar="13" Cut="4.7014278411865234e+01" cType="0" res="-9.9000000000000000e+01" rms="0.0000000000000000e+00" purity="5.3813892602920532e-01" nType="0">
        <Node pos="l" depth="1" NCoef="0" IVar="1" Cut="5.0579959869384766e+01" cType="1" res="-9.9000000000000000e+01" rms="0.0000000000000000e+00" purity="9.0396994352340698e-01" nType="0">
          <Node pos="l" depth="2" NCoef="0" IVar="-1" Cut="1.3018557548522949e+01" cType="0" res="-9.9000000000000000e+01" rms="0.0000000000000000e+00" purity="9.4486194849014282e-01" nType="1"/>
          <Node pos="r" depth="2" NCoef="0" IVar="6" Cut="9.0475887060165405e-01" cType="0" res="-9.9000000000000000e+01" rms="0.0000000000000000e+00" purity="4.5058906078338623e-01" nType="0">
            <Node pos="l" depth="3" NCoef="0" IVar="-1" Cut="0.0000000000000000e+00" cType="1" res="-9.9000000000000000e+01" rms="0.0000000000000000e+00" purity="5.9333294630050659e-01" nType="1"/>
            <Node pos="r" depth="3" NCoef="0" IVar="-1" Cut="0.0000000000000000e+00" cType="1" res="-9.9000000000000000e+01" rms="0.0000000000000000e+00" purity="3.3918827772140503e-01" nType="-1"/>
          </Node>
        </Node>
        <Node pos="r" depth="1" NCoef="0" IVar="6" Cut="9.0476179122924805e-01" cType="0" res="-9.9000000000000000e+01" rms="0.0000000000000000e+00" purity="4.8718258738517761e-01" nType="0">
          <Node pos="l" depth="2" NCoef="0" IVar="1" Cut="3.0766838073730469e+01" cType="1" res="-9.9000000000000000e+01" rms="0.0000000000000000e+00" purity="6.1500275135040283e-01" nType="0">
            <Node pos="l" depth="3" NCoef="0" IVar="-1" Cut="0.0000000000000000e+00" cType="1" res="-9.9000000000000000e+01" rms="0.0000000000000000e+00" purity="6.6545552015304565e-01" nType="1"/>
            <Node pos="r" depth="3" NCoef="0" IVar="-1" Cut="0.0000000000000000e+00" cType="1" res="-9.9000000000000000e+01" rms="0.0000000000000000e+00" purity="3.3900743722915649e-01" nType="-1"/>
          </Node>
          <Node pos="r" depth="2" NCoef="0" IVar="4" Cut="5.0708766937255859e+01" cType="0" res="-9.9000000000000000e+01" rms="0.0000000000000000e+00" purity="4.5751982927322388e-01" nType="0">
            <Node pos="l" depth="3" NCoef="0" IVar="-1" Cut="0.0000000000000000e+00" cType="1" res="-9.9000000000000000e+01" rms="0.0000000000000000e+00" purity="7.2543257474899292e-01" nType="1"/>
            <Node pos="r" depth="3" NCoef="0" IVar="-1" Cut="0.0000000000000000e+00" cType="1" res="-9.9000000000000000e+01" rms="0.0000000000000000e+00" purity="4.2759087681770325e-01" nType="-1"/>
          </Node>
        </Node>
      </Node>
    </BinaryTree>
    <BinaryTree type="DecisionTree" boostWeight="1.9748112265852849e-01" itree="5">
      <Node pos="s" depth="0" NCoef="0" IVar="13" Cut="4.7014278411865234e+01" cType="0" res="-9.9000000000000000e+01" rms="0.0000000000000000e+00" purity="5.6556171178817749e-01" nType="0">
        <Node pos="l" depth="1" NCoef="0" IVar="1" Cut="5.0579959869384766e+01" cType="1" res="-9.9000000000000000e+01" rms="0.0000000000000000e+00" purity="8.8513809442520142e-01" nType="0">
          <Node pos="l" depth="2" NCoef="0" IVar="-1" Cut="2.5999300003051758e+01" cType="0" res="-9.9000000000000000e+01" rms="0.0000000000000000e+00" purity="9.2766433954238892e-01" nType="1"/>
          <Node pos="r" depth="2" NCoef="0" IVar="1" Cut="7.3443397521972656e+01" cType="1" res="-9.9000000000000000e+01" rms="0.0000000000000000e+00" purity="4.5787224173545837e-01" nType="0">
            <Node pos="l" depth="3" NCoef="0" IVar="-1" Cut="0.0000000000000000e+00" cType="1" res="-9.9000000000000000e+01" rms="0.0000000000000000e+00" purity="5.6421679258346558e-01" nType="1"/>
            <Node pos="r" depth="3" NCoef="0" IVar="-1" Cut="0.0000000000000000e+00" cType="1" res="-9.9000000000000000e+01" rms="0.0000000000000000e+00" purity="3.6509764194488525e-01" nType="-1"/>
          </Node>
        </Node>
        <Node pos="r" depth="1" NCoef="0" IVar="15" Cut="2.9416245222091675e-01" cType="1" res="-9.9000000000000000e+01" rms="0.0000000000000000e+00" purity="5.2522796392440796e-01" nType="0">
          <Node pos="l" depth="2" NCoef="0" IVar="15" Cut="1.4012722671031952e-01" cType="0" res="-9.9000000000000000e+01" rms="0.0000000000000000e+00" purity="5.3625869750976562e-01" nType="0">
            <Node pos="l" depth="3" NCoef="0" IVar="-1" Cut="0.0000000000000000e+00" cType="1" res="-9.9000000000000000e+01" rms="0.0000000000000000e+00" purity="5.7220983505249023e-01" nType="1"/>
            <Node pos="r" depth="3" NCoef="0" IVar="-1" Cut="0.0000000000000000e+00" cType="1" res="-9.9000000000000000e+01" rms="0.0000000000000000e+00" purity="4.7823002934455872e-01" nType="-1"/>
          </Node>
          <Node pos="r" depth="2" NCoef="0" IVar="-1" Cut="1.3504981994628906e+01" cType="1" res="-9.9000000000000000e+01" rms="0.0000000000000000e+00" purity="3.1374007463455200e-01" nType="-1"/>
        </Node>
      </Node>
    </BinaryTree>
    <BinaryTree type="DecisionTree" boostWeight="1.3444580954932514e-01" itree="6">
      <Node pos="s" depth="0" NCoef="0" IVar="13" Cut="4.7014278411865234e+01" cType="0" res="-9.9000000000000000e+01" rms="0.0000000000000000e+00" purity="5.5402684211730957e-01" nType="0">
        <Node pos="l" depth="1" NCoef="0" IVar="-1" Cut="2.5310174942016602e+01" cType="1" res="-9.9000000000000000e+01" rms="0.0000000000000000e+00" purity="8.6965930461883545e-01" nType="1"/>
        <Node pos="r" depth="1" NCoef="0" IVar="13" Cut="3.1340234756469727e+01" cType="0" res="-9.9000000000000000e+01" rms="0.0000000000000000e+00" purity="5.1687788963317871e-01" nType="0">
          <Node pos="l" depth="2" NCoef="0" IVar="1" Cut="1.7180635452270508e+01" cType="1" res="-9.9000000000000000e+01" rms="0.0000000000000000e+00" purity="6.8857377767562866e-01" nType="0">
            <Node pos="l" depth="3" NCoef="0" IVar="-1" Cut="0.0000000000000000e+00" cType="1" res="-9.9000000000000000e+01" rms="0.0000000000000000e+00" purity="8.5677623748779297e-01" nType="1"/>
            <Node pos="r" depth="3" NCoef="0" IVar="-1" Cut="0.0000000000000000e+00" cType="1" res="-9.9000000000000000e+01" rms="0.0000000000000000e+00" purity="4.6178823709487915e-01" nType="-1"/>
          </Node>
          <Node pos="r" depth="2" NCoef="0" IVar="4" Cut="1.7907974243164062e+02" cType="0" res="-9.9000000000000000e+01" rms="0.0000000000000000e+00" purity="5.0585514307022095e-01" nType="0">
            <Node pos="l" depth="3" NCoef="0" IVar="-1" Cut="0.0000000000000000e+00" cType="1" res="-9.9000000000000000e+01" rms="0.0000000000000000e+00" purity="9.3821263313293457e-01" nType="1"/>
            <Node pos="r" depth="3" NCoef="0" IVar="-1" Cut="0.0000000000000000e+00" cType="1" res="-9.9000000000000000e+01" rms="0.0000000000000000e+00" purity="4.9324429035186768e-01" nType="-1"/>
          </Node>
        </Node>
      </Node>
    </BinaryTree>
    <BinaryTree type="DecisionTree" boostWeight="1.8139958961121591e-01" itree="7">
      <Node pos="s" depth="0" NCoef="0" IVar="13" Cut="4.7014278411865234e+01" cType="0" res="-9.9000000000000000e+01" rms="0.0000000000000000e+00" purity="5.7753574848175049e-01" nType="0">
        <Node pos="l" depth="1" NCoef="0" IVar="1" Cut="2.5310174942016602e+01" cType="1" res="-9.9000000000000000e+01" rms="0.0000000000000000e+00" purity="8.5364800691604614e-01" nType="0">
          <Node pos="l" depth="2" NCoef="0" IVar="10" Cut="1.7607322692871094e+01" cType="0" res="-9.9000000000000000e+01" rms="0.0000000000000000e+00" purity="9.3241357803344727e-01" nType="0">
            <Node pos="l" depth="3" NCoef="0" IVar="-1" Cut="0.0000000000000000e+00" cType="1" res="-9.9000000000000000e+01" rms="0.0000000000000000e+00" purity="9.5582699775695801e-01" nType="1"/>
            <Node pos="r" depth="3" NCoef="0" IVar="-1" Cut="0.0000000000000000e+00" cType="1" res="-9.9000000000000000e+01" rms="0.0000000000000000e+00" purity="4.8472779989242554e-01" nType="-1"/>
          </Node>
          <Node pos="r" depth="2" NCoef="0" IVar="4" Cut="1.6087944030761719e+02" cType="0" res="-9.9000000000000000e+01" rms="0.0000000000000000e+00" purity="5.8470636606216431e-01" nType="0">
            <Node pos="l" depth="3" NCoef="0" IVar="-1" Cut="0.0000000000000000e+00" cType="1" res="-9.9000000000000000e+01" rms="0.0000000000000000e+00" purity="8.1936931610107422e-01" nType="1"/>
            <Node pos="r" depth="3" NCoef="0" IVar="-1" Cut="0.0000000000000000e+00" cType="1" res="-9.9000000000000000e+01" rms="0.0000000000000000e+00" purity="4.8123335838317871e-01" nType="-1"/>
          </Node>
        </Node>
        <Node pos="r" depth="1" NCoef="0" IVar="8" Cut="3.6977226257324219e+01" cType="0" res="-9.9000000000000000e+01" rms="0.0000000000000000e+00" purity="5.4652112722396851e-01" nType="0">
          <Node pos="l" depth="2" NCoef="0" IVar="13" Cut="4.4768476486206055e+00" cType="1" res="-9.9000000000000000e+01" rms="0.0000000000000000e+00" purity="6.6805809736251831e-01" nType="0">
            <Node pos="l" depth="3" NCoef="0" IVar="-1" Cut="0.0000000000000000e+00" cType="1" res="-9.9000000000000000e+01" rms="0.0000000000000000e+00" purity="8.7718051671981812e-01" nType="1"/>
            <Node pos="r" depth="3" NCoef="0" IVar="-1" Cut="0.0000000000000000e+00" cType="1" res="-9.9000000000000000e+01" rms="0.0000000000000000e+00" purity="2.9807162284851074e-01" nType="-1"/>
          </Node>
          <Node pos="r" depth="2" NCoef="0" IVar="-1" Cut="1.1192945480346680e+01" cType="0" res="-9.9000000000000000e+01" rms="0.0000000000000000e+00" purity="5.3487181663513184e-01" nType="1"/>
        </Node>
      </Node>
    </BinaryTree>
    <BinaryTree type="DecisionTree" boostWeight="2.0171426094632897e-01" itree="8">
      <Node pos="s" depth="0" NCoef="0" IVar="13" Cut="4.7014278411865234e+01" cType="0" res="-9.9000000000000000e+01" rms="0.0000000000000000e+00" purity="5.3727024793624878e-01" nType="0">
        <Node pos="l" depth="1" NCoef="0" IVar="1" Cut="5.0579959869384766e+01" cType="1" res="-9.9000000000000000e+01" rms="0.0000000000000000e+00" purity="8.4888583421707153e-01" nType="0">
          <Node pos="l" depth="2" NCoef="0" IVar="-1" Cut="2.5999300003051758e+01" cType="0" res="-9.9000000000000000e+01" rms="0.0000000000000000e+00" purity="8.9643812179565430e-01" nType="1"/>
          <Node pos="r" depth="2" NCoef="0" IVar="-1" Cut="2.5787359237670898e+01" cType="1" res="-9.9000000000000000e+01" rms="0.0000000000000000e+00" purity="4.5023426413536072e-01" nType="-1"/>
        </Node>
        <Node pos="r" depth="1" NCoef="0" IVar="8" Cut="3.6977226257324219e+01" cType="0" res="-9.9000000000000000e+01" rms="0.0000000000000000e+00" purity="5.0419712066650391e-01" nType="0">
          <Node pos="l" depth="2" NCoef="0" IVar="13" Cut="4.4768476486206055e+00" cType="1" res="-9.9000000000000000e+01" rms="0.0000000000000000e+00" purity="6.6485667228698730e-01" nType="0">
            <Node pos="l" depth="3" NCoef="0" IVar="-1" Cut="0.0000000000000000e+00" cType="1" res="-9.9000000000000000e+01" rms="0.0000000000000000e+00" purity="8.5626369714736938e-01" nType="1"/>
            <Node pos="r" depth="3" NCoef="0" IVar="-1" Cut="0.0000000000000000e+00" cType="1" res="-9.9000000000000000e+01" rms="0.0000000000000000e+00" purity="3.3735626935958862e-01" nType="-1"/>
          </Node>
          <Node pos="r" depth="2" NCoef="0" IVar="13" Cut="1.1192945480346680e+01" cType="0" res="-9.9000000000000000e+01" rms="0.0000000000000000e+00" purity="4.8958012461662292e-01" nType="0">
            <Node pos="l" depth="3" NCoef="0" IVar="-1" Cut="0.0000000000000000e+00" cType="1" res="-9.9000000000000000e+01" rms="0.0000000000000000e+00" purity="5.8295053243637085e-01" nType="1"/>
            <Node pos="r" depth="3" NCoef="0" IVar="-1" Cut="0.0000000000000000e+00" cType="1" res="-9.9000000000000000e+01" rms="0.0000000000000000e+00" purity="4.5780211687088013e-01" nType="-1"/>
          </Node>
        </Node>
      </Node>
    </BinaryTree>
    <BinaryTree type="DecisionTree" boostWeight="1.6140247582309619e-01" itree="9">
      <Node pos="s" depth="0" NCoef="0" IVar="13" Cut="4.7014278411865234e+01" cType="0" res="-9.9000000000000000e+01" rms="0.0000000000000000e+00" purity="5.5406016111373901e-01" nType="0">
        <Node pos="l" depth="1" NCoef="0" IVar="10" Cut="2.5979932785034180e+01" cType="0" res="-9.9000000000000000e+01" rms="0.0000000000000000e+00" purity="8.3343714475631714e-01" nType="0">
          <Node pos="l" depth="2" NCoef="0" IVar="1" Cut="5.0579959869384766e+01" cType="1" res="-9.9000000000000000e+01" rms="0.0000000000000000e+00" purity="9.0079712867736816e-01" nType="0">
            <Node pos="l" depth="3" NCoef="0" IVar="-1" Cut="0.0000000000000000e+00" cType="1" res="-9.9000000000000000e+01" rms="0.0000000000000000e+00" purity="9.3551403284072876e-01" nType="1"/>
            <Node pos="r" depth="3" NCoef="0" IVar="-1" Cut="0.0000000000000000e+00" cType="1" res="-9.9000000000000000e+01" rms="0.0000000000000000e+00" purity="4.9197617173194885e-01" nType="-1"/>
          </Node>
          <Node pos="r" depth="2" NCoef="0" IVar="4" Cut="1.0148238372802734e+02" cType="0" res="-9.9000000000000000e+01" rms="0.0000000000000000e+00" purity="5.4898297786712646e-01" nType="0">
            <Node pos="l" depth="3" NCoef="0" IVar="-1" Cut="0.0000000000000000e+00" cType="1" res="-9.9000000000000000e+01" rms="0.0000000000000000e+00" purity="8.3353406190872192e-01" nType="1"/>
            <Node pos="r" depth="3" NCoef="0" IVar="-1" Cut="0.0000000000000000e+00" cType="1" res="-9.9000000000000000e+01" rms="0.0000000000000000e+00" purity="3.3049830794334412e-01" nType="-1"/>
          </Node>
        </Node>
        <Node pos="r" depth="1" NCoef="0" IVar="8" Cut="3.6977226257324219e+01" cType="0" res="-9.9000000000000000e+01" rms="0.0000000000000000e+00" purity="5.2614802122116089e-01" nType="0">
          <Node pos="l" depth="2" NCoef="0" IVar="13" Cut="6.7151780128479004e+00" cType="1" res="-9.9000000000000000e+01" rms="0.0000000000000000e+00" purity="6.6088843345642090e-01" nType="0">
            <Node pos="l" depth="3" NCoef="0" IVar="-1" Cut="0.0000000000000000e+00" cType="1" res="-9.9000000000000000e+01" rms="0.0000000000000000e+00" purity="8.1331497430801392e-01" nType="1"/>
            <Node pos="r" depth="3" NCoef="0" IVar="-1" Cut="0.0000000000000000e+00" cType="1" res="-9.9000000000000000e+01" rms="0.0000000000000000e+00" purity="3.4455499053001404e-01" nType="-1"/>
          </Node>
          <Node pos="r" depth="2" NCoef="0" IVar="1" Cut="3.3483779907226562e+01" cType="1" res="-9.9000000000000000e+01" rms="0.0000000000000000e+00" purity="5.1446783542633057e-01" nType="0">
            <Node pos="l" depth="3" NCoef="0" IVar="-1" Cut="0.0000000000000000e+00" cType="1" res="-9.9000000000000000e+01" rms="0.0000000000000000e+00" purity="5.2585524320602417e-01" nType="1"/>
            <Node pos="r" depth="3" NCoef="0" IVar="-1" Cut="0.0000000000000000e+00" cType="1" res="-9.9000000000000000e+01" rms="0.0000000000000000e+00" purity="3.9841896295547485e-01" nType="-1"/>
          </Node>
        </Node>
      </Node>
    </BinaryTree>
  </Weights>
</MethodSetup>
